consumeraffairs_django_experiments-1.4.4.dist-info/DESCRIPTION.rst
consumeraffairs_django_experiments-1.4.4.dist-info/METADATA
consumeraffairs_django_experiments-1.4.4.dist-info/RECORD
consumeraffairs_django_experiments-1.4.4.dist-info/WHEEL
consumeraffairs_django_experiments-1.4.4.dist-info/metadata.json
consumeraffairs_django_experiments-1.4.4.dist-info/top_level.txt
experiments/__init__.py
experiments/admin.py
experiments/admin_utils.py
experiments/apps.py
experiments/conf.py
experiments/consts.py
experiments/counters.py
experiments/dateutils.py
experiments/experiment_counters.py
experiments/lock.py
experiments/manager.py
experiments/middleware.py
experiments/models.py
experiments/signal_handlers.py
experiments/signals.py
experiments/significance.py
experiments/stats.py
experiments/urls.py
experiments/utils.py
experiments/views.py
experiments/api/__init__.py
experiments/api/admin.py
experiments/api/models.py
experiments/api/urls.py
experiments/api/views.py
experiments/api/tests/__init__.py
experiments/api/tests/test_admin.py
experiments/api/tests/test_models.py
experiments/api/tests/test_root.py
experiments/api/tests/test_v1.py
experiments/api/v1/__init__.py
experiments/api/v1/paginators.py
experiments/api/v1/serializers.py
experiments/api/v1/urls.py
experiments/api/v1/views.py
experiments/conditional/__init__.py
experiments/conditional/admin.py
experiments/conditional/enrollment.py
experiments/conditional/models.py
experiments/conditional/utils.py
experiments/conditional/tests/__init__.py
experiments/conditional/tests/test_admin.py
experiments/conditional/tests/test_enrollment.py
experiments/conditional/tests/test_models.py
experiments/conditional/tests/test_utils.py
experiments/migrations/0001_initial.py
experiments/migrations/0002_update_experiment_fields.py
experiments/migrations/0003_conditionals.py
experiments/migrations/0004_api.py
experiments/migrations/0005_experiment_disablement_model.py
experiments/migrations/__init__.py
experiments/static/experiments/dashboard/css/admin.css
experiments/static/experiments/dashboard/js/admin.js
experiments/static/experiments/dashboard/js/change_list.js
experiments/static/experiments/dashboard/js/csrf.js
experiments/static/experiments/js/experiments.js
experiments/static/import_export/action_formats.js
