Metadata-Version: 2.0
Name: consumeraffairs-django-experiments
Version: 1.4.4
Summary: Python Django AB Testing Framework
Home-page: https://github.com/ConsumerAffairs/django-experiments
Author: ConsumerAffairs
Author-email: dev@consumeraffairs.com
License: MIT
Platform: UNKNOWN
Classifier: Development Status :: 5 - Production/Stable
Classifier: Intended Audience :: Developers
Classifier: License :: OSI Approved :: MIT License
Classifier: Topic :: Internet :: WWW/HTTP
Classifier: Topic :: Software Development :: Libraries
Classifier: Programming Language :: Python :: 2
Classifier: Programming Language :: Python :: 2.7
Classifier: Programming Language :: Python :: 3
Classifier: Programming Language :: Python :: 3.5
Classifier: Programming Language :: Python :: 3.6
Classifier: Framework :: Django
Classifier: Framework :: Django :: 1.8
Classifier: Framework :: Django :: 1.9
Classifier: Framework :: Django :: 1.10
Classifier: Framework :: Django :: 1.11
Requires-Dist: Markdown (>=2.6.10,<2.7)
Requires-Dist: django (>=1.8,<2)
Requires-Dist: django-import-export (==0.5.1)
Requires-Dist: django-jinja (>=2.3.1)
Requires-Dist: django-jsonfield (>=1.0.1)
Requires-Dist: django-modeldict-yplan (>=1.5.0)
Requires-Dist: djangorestframework (<3.7,>=3.6.4)
Requires-Dist: lxml (<5,>=4.1.1)
Requires-Dist: redis (>=2.4.9)
Requires-Dist: requests (>2.18,<2.19)
Requires-Dist: six (>=1.10.0)
